Workbook

Sheet README
A1: Pravah: component and Google service map
A2: Companion to docs/SPEC.md (build specification v1.0, 14 Oct 2026). Stage IDs (S0–S19) match the spec.
A4: How to use
A5: 1. Components: one row per stage / component / logic piece, with the Google service it uses. Build top to bottom.
A6: 2. Only edit the yellow 'Status' column (dropdown: Not started, In progress, Done, Blocked). Progress updates automatically.
A7: 3. Google services: every Google service the platform uses and what it is for.
A8: 4. Data sources: every dataset with its access ID, licence and whether its ID was verified on 14 Oct 2026.
A9: 5. Compliance: challenge rules and Google Maps Platform terms, and how the design complies.
A10: 6. Day plan and Progress: schedule and live completion by stage.
A12: Rules this sheet enforces
A13: • AI = Gemini only (Vertex AI, ADK). Hosting = Cloud Run + Firebase Hosting. Data/compute/storage = Google Cloud.
A14: • Non-Google items are open-source libraries or open data (mainly OpenStreetMap). Each is flagged in the 'Non-Google element' column with its reason.
... A18: C27 | S3 | Rational method runoff | Q = 0.278·C·i·A | C (Dynamic World), rain mm/h, A_local km² | Q per reach per hour | Cloud Run (compute) | engine code; inputs from Earth Engine | — | — | Compliant | N/A | P0 | Thu 15 | C26, C21 | Not started

Sheet Components
A1: ID | B1: Stage | C1: Component | D1: Logic / method | E1: Inputs | F1: Outputs | G1: Google service(s) | H1: Specific API / dataset / product | I1: Non-Google element | J1: Why allowed | K1: Challenge-rule check | L1: Maps ToS check | M1: Priority | N1: Build day | O1: Depends on | P1: Status
A2: C01 | B2: S0 | C2: Backend hosting | D2: FastAPI app in a container; --no-cpu-throttling, 4 GiB, 900 s timeout | E2: Code | F2: Public HTTPS API | G2: Cloud Run; Cloud Build; Artifact Registry | H2: Cloud Run service pravah-backend (asia-south1) | I2: FastAPI (open-source) | J2: Library, not a model or host | K2: Compliant (required host) | L2: N/A | M2: P0 | N2: Wed 14 | O2: — | P2: Not started
A3: C02 | B3: S0 | C3: Frontend hosting | D3: Static React build; /api/** rewrite to Cloud Run | E3: Built frontend | F3: Public web app | G3: Firebase Hosting | H3: firebase.json rewrite → run.serviceId | I3: React, Vite (open-source) | J3: Libraries | K3: Compliant (required host) | L3: N/A | M3: P0 | N3: Wed 14 | O3: C01 | P3: Not started
A4: C03 | B4: S0 | C4: Keys and secrets | D4: Browser key (referrer-restricted), server key (API-restricted) in Secret Manager | E4: — | F4: Restricted keys | G4: Secret Manager; API Keys; IAM | H4: maps-server-key secret; service account pravah-backend | I4: — | J4: — | K4: Compliant | L4: Keys restricted per Maps best practice | M4: P0 | N4: Wed 14 | O4: — | P4: Not started
A5: C04 | B5: S0 | C5: Budget guardrail | D5: Budget $100 with 25/50/75/100% alerts | E5: — | F5: Email alerts | G5: Cloud Billing | H5: Budgets & alerts | I5: — | J5: — | K5: Compliant | L5: N/A | M5: P0 | N5: Wed 14 | O5: — | P5: Not started
A6: C05 | B6: S0 | C6: Model selection | D6: List available models, human picks Fast and Pro | E6: — | F6: GEMINI_MODEL_FAST / _PRO env vars | G6: Vertex AI | H6: google-genai client.models.list() | I6: — | J6: — | K6: Compliant (Gemini) | L6: N/A | M6: P0 | N6: Wed 14 | O6: C01 | P6: Not started
A7: C06 | B7: S1 | C7: AOI capture and validation | D7: sha1 id, size limits (river ≤15 km, urban ≤4 km) | E7: Drawn bbox | F7: AOI doc | G7: Firestore; Cloud Run | H7: aois/{aoi_id} | I7: — | J7: — | K7: Compliant | L7: N/A | M7: P0 | N7: Wed 14 | O7: C01 | P7: Not started
A8: C07 | B8: S1 | C8: Analysis grid (UTM, 30 m) | D8: GridSpec, transforms, 4-corner overlay bounds | E8: AOI bbox | F8: GridSpec | G8: Cloud Run (compute) | H8: engines/grid.py | I8: pyproj (open-source) | J8: Library | K8: Compliant | L8: N/A | M8: P0 | N8: Wed 14 | O8: C06 | P8: Not started
A9: C08 | B9: S1 | C9: Terrain: DEM, slope, aspect, curvature | D9: computePixels to the grid; NumPy derivatives | E9: AOI grid | F9: dem, slope_deg, aspect_deg, curv | G9: Earth Engine (noncommercial) | H9: Copernicus DEM GLO-30 (COPERNICUS/DEM/GLO30 deprecated → successor GLO30_2024_1, VERIFY) | I9: NumPy | J9: Library | K9: Compliant | L9: Not Maps content (Elevation API deliberately NOT used, §3.2.3(c)(iii)) | M9: P0 | N9: Wed 14 | O9: C07 | P9: Not started
A10: C09 | B10: S1 | C10: Hydrology layers: HAND, D8, upstream area | D10: computePixels; bilinear for hnd/elv, nearest for dir/upa | E10: AOI grid | F10: hand, d8, upa, elv_hydro | G10: Earth Engine (noncommercial) | H10: MERIT/Hydro/v1_0_1 (hnd, dir, upa, elv) | I10: — | J10: — | K10: Compliant | L10: N/A | M10: P0 | N10: Wed 14 | O10: C07 | P10: Not started
A11: C10 | B11: S1 | C11: Land cover | D11: Mode of last 12 months of labels | E11: AOI | F11: lc_class (0–8) | G11: Earth Engine (noncommercial) | H11: GOOGLE/DYNAMICWORLD/V1 label | I11: — | J11: — | K11: Compliant | L11: N/A | M11: P0 | N11: Wed 14 | O11: C07 | P11: Not started
A12: C11 | B12: S1 | C12: Vegetation (NDVI) | D12: Dry-season median, cloud < 20% | E12: AOI | F12: ndvi | G12: Earth Engine (noncommercial) | H12: COPERNICUS/S2_SR_HARMONIZED B8/B4 | I12: — | J12: — | K12: Compliant | L12: N/A | M12: P1 | N12: Wed 14 | O12: C07 | P12: Not started
... A86: C85 | B86: S19 | C86: Photorealistic 3D backdrop (OPT) | D86: 3D Maps where coverage exists | E86: — | F86: 3D backdrop | G86: Google Maps Platform | H86: Map Tiles API / Maps JS 3D Maps (VERIFY API, coverage) | I86: — | J86: — | K86: Compliant | L86: Display only | M86: OPT | N86: Sun 18 | O86: C84 | P86: Not started

Sheet Google services
A1: Google service | B1: Used for | C1: Component IDs | D1: Billing / credit | E1: Spec section | F1: Notes
A2: Cloud Run | B2: Backend API + all engine compute + ADK agents | C2: C01, C06–C70, C81 | D2: Trial credit ($300, 90 days) | E2: S0.12, S17.1 | F2: Required host by challenge rules. Region asia-south1.
A3: Firebase Hosting | B3: Frontend web app; /api rewrite to Cloud Run | C3: C02, C71–C80 | D3: Free tier / trial credit | E3: S0.13, S17.2 | F3: Required host option by challenge rules.
A4: Vertex AI: Gemini (Flash) | B4: Scenario planner, analyst chat, photo classifier, historian | C4: C05, C57, C60, C65, C66 | D4: Trial credit | E4: S0.10, S14.8 | F4: Model name picked from the live model list. Never hardcoded.
A5: Vertex AI: Gemini (Pro) | B5: Advisory brief (structured output) | C5: C69 | D5: Trial credit | E5: S15.2 | F5: Structured output with response_schema.
A6: Agent Development Kit (ADK) | B6: Agents, function tools, runner, sessions, SequentialAgent | C6: C64–C67, C57 | D6: Open-source framework (runs on Cloud Run) | E6: S14 | F6: Google's agent platform, matching the challenge's 'agentic' track.
A7: Grounding with Google Search | B7: Historian agent finds documented past incidents with sources | C7: C57 | D7: Billed per grounded request (VERIFY price) | E7: S11.4 | F7: Show grounding attributions as required (VERIFY).
A8: Earth Engine | B8: All geospatial analysis data: DEM, HAND, land cover, population, buildings, rainfall, floods, landslides; map tiles | C8: C08–C16, C20, C33, C52–C56, C82, C84 | D8: Noncommercial: not charged; quota 150–1,000 EECU-h/month | E8: S0.3, S1, S2 | F8: Register the project as noncommercial. Some datasets are CC-BY-NC.
A9: Cloud Storage | B9: Layer cache (.npz), overlay PNGs, run arrays, photos | C9: C17–C19, C29, C46, C59 | D9: Trial credit | E9: S0.5, S1.11 | F9: Private bucket; signed URLs.
A10: Firestore | B10: AOIs, runs, advisories, photo results, history cache | C10: C06, C18, C59, C63, C70 | D10: Free tier / trial credit | E10: S0.5 | F10: Native mode, asia-south1.
A11: Secret Manager | B11: Server API key | C11: C03 | D11: Trial credit | E11: S0.6 | F11: Mounted as an env var on Cloud Run.
A12: Cloud Build + Artifact Registry | B12: Container builds for Cloud Run | C12: C01, C81 | D12: Trial credit | E12: S0.12 | F12: gcloud run deploy --source.
... A18: Map Tiles API (Maps Platform) | B18: Photorealistic 3D backdrop (optional) | C18: C85 | D18: Maps free usage + trial credit | E18: S19.2 | F18: Optional; VERIFY coverage over the demo AOI.

Sheet Data sources
A1: Dataset | B1: Provider | C1: Access ID / endpoint | D1: Resolution | E1: Period | F1: Licence | G1: Used in | H1: ID check
A2: Copernicus DEM GLO-30 | B2: ESA / Copernicus | C2: Earth Engine: COPERNICUS/DEM/GLO30 (marked deprecated; successor COPERNICUS/DEM/GLO30_2024_1) | D2: 30 m | E2: — | F2: Free licence (except Armenia/Azerbaijan) | G2: C08, C84 | H2: Verified 14 Oct (successor ID: VERIFY)
A3: MERIT Hydro v1.0.1 (hnd, dir, upa, elv) | B3: Yamazaki et al. | C3: Earth Engine: MERIT/Hydro/v1_0_1 | D3: ~90 m (3″) | E3: — | F3: CC-BY-NC 4.0 or ODbL 1.0 | G3: C09, C20–C23 | H3: Verified 14 Oct
A4: Open Buildings v3 polygons | B4: Google Research | C4: Earth Engine: GOOGLE/Research/open-buildings/v3/polygons | D4: Vector | E4: — | F4: CC-BY 4.0 | G4: C16, C36 | H4: Verified 14 Oct (India coverage: check count)
A5: Open Buildings 2.5D Temporal | B5: Google Research | C5: Earth Engine: GOOGLE/Research/open-buildings-temporal/v1 | D5: 4 m effective | E5: 2016–2023 | F5: CC-BY 4.0 or ODbL | G5: C16, C36, C84 | H5: Verified 14 Oct
A6: WorldPop population | B6: WorldPop | C6: Earth Engine: WorldPop/GP/100m/pop | D6: 100 m | E6: Latest year: VERIFY | F6: VERIFY (typically CC-BY 4.0) | G6: C15, C37 | H6: ID verified 14 Oct
A7: Global Flood Database v1 | B7: Cloud to Street / Tellman et al. | C7: Earth Engine: GLOBAL_FLOOD_DB/MODIS_EVENTS/V1 | D7: 250 m classification | E7: 2000–2018 | F7: CC-BY-NC 4.0 | G7: C14, C54, C56, C58 | H7: Verified 14 Oct
A8: CHIRPS daily rainfall | B8: UCSB Climate Hazards Center | C8: Earth Engine: UCSB-CHG/CHIRPS/DAILY | D8: 0.05° | E8: 1981 → ~2026 | F8: VERIFY | G8: C13, C53 | H8: Verified 14 Oct
A9: GPM IMERG V07 | B9: NASA | C9: Earth Engine: NASA/GPM_L3/IMERG_V07 | D9: 0.1°, half-hourly (mm/h) | E9: 1998 → near real time | F9: NASA open data | G9: C52 | H9: Verified 14 Oct
A10: Dynamic World land cover | B10: Google / WRI | C10: Earth Engine: GOOGLE/DYNAMICWORLD/V1 | D10: 10 m | E10: 2015 → present | F10: VERIFY (CC-BY 4.0) | G10: C10, C26 | H10: VERIFY
A11: Sentinel-2 SR (harmonized) | B11: ESA / Copernicus | C11: Earth Engine: COPERNICUS/S2_SR_HARMONIZED | D11: 10 m | E11: 2017 → present | F11: Copernicus open licence | G11: C11 | H11: VERIFY
A12: JRC Global Surface Water | B12: EC JRC | C12: Earth Engine: JRC/GSW1_4/GlobalSurfaceWater (VERIFY latest) | D12: 30 m | E12: 1984 → ~2021 | F12: VERIFY | G12: C14 | H12: VERIFY
... A17: Field photos | B17: Authorities / project owner | C17: User upload | D17: Photo | E17: — | F17: Owner's own images or openly licensed with attribution | G17: C59, C60 | H17: —

Sheet Compliance
A1: Area | B1: Rule | C1: Source | D1: How we comply | E1: Open risk / action
A2: Challenge | B2: Use Google AI models (Gemini/Gemma) or Google agentic platforms | C2: Event listing (Metropolis, Hack2skill) | D2: Gemini on Vertex AI for every AI step; agents built with ADK | E2: None
A3: Challenge | B3: Deploy on Google Cloud via Cloud Run or Firebase | C3: Event listing | D3: Backend on Cloud Run; frontend on Firebase Hosting | E3: None
A4: Challenge | B4: Team of 2–4, all 21+ | C4: Event listings | D4: Confirm the second member has joined on the dashboard | E4: Team card showed an empty slot
A5: Challenge | B5: Prototype due 18 Oct 2026 | C5: Hack2skill dashboard | D5: Submit by 12:00 IST Sunday | E5: Check the required submission format
A6: Maps ToS §3.2.3(a) | B6: No scraping, bulk download of Street View images or elevation values | C6: cloud.google.com/maps-platform/terms | D6: No Street View/elevation extraction; analysis data from Earth Engine + OSM | E6: None
A7: Maps ToS §3.2.3(b) | B7: No caching except as permitted | C7: Same | D7: Weather responses held in memory 10 min; runs store the scenario label + series used | E7: VERIFY Weather API service-specific caching terms
A8: Maps ToS §3.2.3(c)(iii) | B8: No terrain models from Elevation API values | C8: Same | D8: Terrain/slope/HAND from Copernicus DEM + MERIT in Earth Engine; Elevation API not used | E8: None
A9: Maps ToS §3.2.3(c)(iv) | B9: No Places API lat/lng in point-in-polygon analysis | C9: Same | D9: Shelters, POIs and crowding from OpenStreetMap | E9: None
A10: Maps ToS §3.2.3(c)(v) | B10: No indexes built from Street View imagery | C10: Same | D10: Building/drain classification from authorities' own field photos; Street View is human viewing only | E10: Changed from the earlier plan; explain in the pitch
A11: Maps ToS §3.2.3(c)(vii) | B11: No Maps content to train/test/fine-tune AI | C11: Same | D11: No Maps content goes to Gemini | E11: None
A12: Earth Engine | B12: Noncommercial registration and quota | C12: developers.google.com/earth-engine/guides/noncommercial_tiers | D12: Register as noncommercial research prototype; monitor EECU use | E12: Commercial use later needs a commercial EE plan
... A16: Privacy | B16: No personal data; no inference about people | C16: Project decision | D16: Photos are of structures/drains only; avoid faces; classify structures, never people | E16: Demo photos must be the owner's own or openly licensed

Sheet Day plan
A1: Day | B1: Stages | C1: Checkpoint | D1: Components planned | E1: Components done | F1: % done
A2: Wed 14 Oct | B2: S0, S1, S2, S3-M1 | C2: Draw an AOI → layers prepared → flood depth from a stage slider on the Google map (deployed) | D2: =COUNTIFS(Components!$N$2:$N$86,"Wed 14") -> 26 | E2: =COUNTIFS(Components!$N$2:$N$86,"Wed 14",Components!$P$2:$P$86,"Done") -> 0 | F2: =IF(D2=0,0,E2/D2) -> 0
A3: Thu 15 Oct | B3: S3 M2–M4, S4, S5, S6 | C3: Rain scenario → hourly flood + landslide susceptibility + exposure numbers | D3: =COUNTIFS(Components!$N$2:$N$86,"Thu 15") -> 17 | E3: =COUNTIFS(Components!$N$2:$N$86,"Thu 15",Components!$P$2:$P$86,"Done") -> 0 | F3: =IF(D3=0,0,E3/D3) -> 0
A4: Fri 16 Oct | B4: S7, S8, S9, S10, S16 Workspace | C4: Full what-if loop: close shelter / block road → reroute, capacity gap | D4: =COUNTIFS(Components!$N$2:$N$86,"Fri 16") -> 15 | E4: =COUNTIFS(Components!$N$2:$N$86,"Fri 16",Components!$P$2:$P$86,"Done") -> 0 | F4: =IF(D4=0,0,E4/D4) -> 0
A5: Sat 17 Oct | B5: S14, S15, S11, S12, S13, S16 pages, S17 | C5: Advisory + chat + history + photo verify, deployed | D5: =COUNTIFS(Components!$N$2:$N$86,"Sat 17") -> 23 | E5: =COUNTIFS(Components!$N$2:$N$86,"Sat 17",Components!$P$2:$P$86,"Done") -> 0 | F5: =IF(D5=0,0,E5/D5) -> 0
A6: Sun 18 Oct | B6: S18 (+ S19 only if all green) | C6: Submitted by 12:00 IST | D6: =COUNTIFS(Components!$N$2:$N$86,"Sun 18") -> 4 | E6: =COUNTIFS(Components!$N$2:$N$86,"Sun 18",Components!$P$2:$P$86,"Done") -> 0 | F6: =IF(D6=0,0,E6/D6) -> 0

Sheet Progress
A1: Stage | B1: Components | C1: Done | D1: In progress | E1: Blocked | F1: % done
A2: S0 | B2: =COUNTIFS(Components!$B$2:$B$86,"S0") -> 5 | C2: =COUNTIFS(Components!$B$2:$B$86,"S0",Components!$P$2:$P$86,"Done") -> 0 | D2: =COUNTIFS(Components!$B$2:$B$86,"S0",Components!$P$2:$P$86,"In progress") -> 0 | E2: =COUNTIFS(Components!$B$2:$B$86,"S0",Components!$P$2:$P$86,"Blocked") -> 0 | F2: =IF(B2=0,0,C2/B2) -> 0
A3: S1 | B3: =COUNTIFS(Components!$B$2:$B$86,"S1") -> 14 | C3: =COUNTIFS(Components!$B$2:$B$86,"S1",Components!$P$2:$P$86,"Done") -> 0 | D3: =COUNTIFS(Components!$B$2:$B$86,"S1",Components!$P$2:$P$86,"In progress") -> 0 | E3: =COUNTIFS(Components!$B$2:$B$86,"S1",Components!$P$2:$P$86,"Blocked") -> 0 | F3: =IF(B3=0,0,C3/B3) -> 0
A4: S2 | B4: =COUNTIFS(Components!$B$2:$B$86,"S2") -> 5 | C4: =COUNTIFS(Components!$B$2:$B$86,"S2",Components!$P$2:$P$86,"Done") -> 0 | D4: =COUNTIFS(Components!$B$2:$B$86,"S2",Components!$P$2:$P$86,"In progress") -> 0 | E4: =COUNTIFS(Components!$B$2:$B$86,"S2",Components!$P$2:$P$86,"Blocked") -> 0 | F4: =IF(B4=0,0,C4/B4) -> 0
A5: S3 | B5: =COUNTIFS(Components!$B$2:$B$86,"S3") -> 5 | C5: =COUNTIFS(Components!$B$2:$B$86,"S3",Components!$P$2:$P$86,"Done") -> 0 | D5: =COUNTIFS(Components!$B$2:$B$86,"S3",Components!$P$2:$P$86,"In progress") -> 0 | E5: =COUNTIFS(Components!$B$2:$B$86,"S3",Components!$P$2:$P$86,"Blocked") -> 0 | F5: =IF(B5=0,0,C5/B5) -> 0
A6: S4 | B6: =COUNTIFS(Components!$B$2:$B$86,"S4") -> 2 | C6: =COUNTIFS(Components!$B$2:$B$86,"S4",Components!$P$2:$P$86,"Done") -> 0 | D6: =COUNTIFS(Components!$B$2:$B$86,"S4",Components!$P$2:$P$86,"In progress") -> 0 | E6: =COUNTIFS(Components!$B$2:$B$86,"S4",Components!$P$2:$P$86,"Blocked") -> 0 | F6: =IF(B6=0,0,C6/B6) -> 0
A7: S5 | B7: =COUNTIFS(Components!$B$2:$B$86,"S5") -> 4 | C7: =COUNTIFS(Components!$B$2:$B$86,"S5",Components!$P$2:$P$86,"Done") -> 0 | D7: =COUNTIFS(Components!$B$2:$B$86,"S5",Components!$P$2:$P$86,"In progress") -> 0 | E7: =COUNTIFS(Components!$B$2:$B$86,"S5",Components!$P$2:$P$86,"Blocked") -> 0 | F7: =IF(B7=0,0,C7/B7) -> 0
A8: S6 | B8: =COUNTIFS(Components!$B$2:$B$86,"S6") -> 4 | C8: =COUNTIFS(Components!$B$2:$B$86,"S6",Components!$P$2:$P$86,"Done") -> 0 | D8: =COUNTIFS(Components!$B$2:$B$86,"S6",Components!$P$2:$P$86,"In progress") -> 0 | E8: =COUNTIFS(Components!$B$2:$B$86,"S6",Components!$P$2:$P$86,"Blocked") -> 0 | F8: =IF(B8=0,0,C8/B8) -> 0
A9: S7 | B9: =COUNTIFS(Components!$B$2:$B$86,"S7") -> 4 | C9: =COUNTIFS(Components!$B$2:$B$86,"S7",Components!$P$2:$P$86,"Done") -> 0 | D9: =COUNTIFS(Components!$B$2:$B$86,"S7",Components!$P$2:$P$86,"In progress") -> 0 | E9: =COUNTIFS(Components!$B$2:$B$86,"S7",Components!$P$2:$P$86,"Blocked") -> 0 | F9: =IF(B9=0,0,C9/B9) -> 0
A10: S8 | B10: =COUNTIFS(Components!$B$2:$B$86,"S8") -> 3 | C10: =COUNTIFS(Components!$B$2:$B$86,"S8",Components!$P$2:$P$86,"Done") -> 0 | D10: =COUNTIFS(Components!$B$2:$B$86,"S8",Components!$P$2:$P$86,"In progress") -> 0 | E10: =COUNTIFS(Components!$B$2:$B$86,"S8",Components!$P$2:$P$86,"Blocked") -> 0 | F10: =IF(B10=0,0,C10/B10) -> 0
A11: S9 | B11: =COUNTIFS(Components!$B$2:$B$86,"S9") -> 2 | C11: =COUNTIFS(Components!$B$2:$B$86,"S9",Components!$P$2:$P$86,"Done") -> 0 | D11: =COUNTIFS(Components!$B$2:$B$86,"S9",Components!$P$2:$P$86,"In progress") -> 0 | E11: =COUNTIFS(Components!$B$2:$B$86,"S9",Components!$P$2:$P$86,"Blocked") -> 0 | F11: =IF(B11=0,0,C11/B11) -> 0
A12: S10 | B12: =COUNTIFS(Components!$B$2:$B$86,"S10") -> 5 | C12: =COUNTIFS(Components!$B$2:$B$86,"S10",Components!$P$2:$P$86,"Done") -> 0 | D12: =COUNTIFS(Components!$B$2:$B$86,"S10",Components!$P$2:$P$86,"In progress") -> 0 | E12: =COUNTIFS(Components!$B$2:$B$86,"S10",Components!$P$2:$P$86,"Blocked") -> 0 | F12: =IF(B12=0,0,C12/B12) -> 0
A13: S11 | B13: =COUNTIFS(Components!$B$2:$B$86,"S11") -> 5 | C13: =COUNTIFS(Components!$B$2:$B$86,"S11",Components!$P$2:$P$86,"Done") -> 0 | D13: =COUNTIFS(Components!$B$2:$B$86,"S11",Components!$P$2:$P$86,"In progress") -> 0 | E13: =COUNTIFS(Components!$B$2:$B$86,"S11",Components!$P$2:$P$86,"Blocked") -> 0 | F13: =IF(B13=0,0,C13/B13) -> 0
A14: S12 | B14: =COUNTIFS(Components!$B$2:$B$86,"S12") -> 2 | C14: =COUNTIFS(Components!$B$2:$B$86,"S12",Components!$P$2:$P$86,"Done") -> 0 | D14: =COUNTIFS(Components!$B$2:$B$86,"S12",Components!$P$2:$P$86,"In progress") -> 0 | E14: =COUNTIFS(Components!$B$2:$B$86,"S12",Components!$P$2:$P$86,"Blocked") -> 0 | F14: =IF(B14=0,0,C14/B14) -> 0
A15: S13 | B15: =COUNTIFS(Components!$B$2:$B$86,"S13") -> 2 | C15: =COUNTIFS(Components!$B$2:$B$86,"S13",Components!$P$2:$P$86,"Done") -> 0 | D15: =COUNTIFS(Components!$B$2:$B$86,"S13",Components!$P$2:$P$86,"In progress") -> 0 | E15: =COUNTIFS(Components!$B$2:$B$86,"S13",Components!$P$2:$P$86,"Blocked") -> 0 | F15: =IF(B15=0,0,C15/B15) -> 0
A16: S14 | B16: =COUNTIFS(Components!$B$2:$B$86,"S14") -> 5 | C16: =COUNTIFS(Components!$B$2:$B$86,"S14",Components!$P$2:$P$86,"Done") -> 0 | D16: =COUNTIFS(Components!$B$2:$B$86,"S14",Components!$P$2:$P$86,"In progress") -> 0 | E16: =COUNTIFS(Components!$B$2:$B$86,"S14",Components!$P$2:$P$86,"Blocked") -> 0 | F16: =IF(B16=0,0,C16/B16) -> 0
A17: S15 | B17: =COUNTIFS(Components!$B$2:$B$86,"S15") -> 3 | C17: =COUNTIFS(Components!$B$2:$B$86,"S15",Components!$P$2:$P$86,"Done") -> 0 | D17: =COUNTIFS(Components!$B$2:$B$86,"S15",Components!$P$2:$P$86,"In progress") -> 0 | E17: =COUNTIFS(Components!$B$2:$B$86,"S15",Components!$P$2:$P$86,"Blocked") -> 0 | F17: =IF(B17=0,0,C17/B17) -> 0
A18: S16 | B18: =COUNTIFS(Components!$B$2:$B$86,"S16") -> 10 | C18: =COUNTIFS(Components!$B$2:$B$86,"S16",Components!$P$2:$P$86,"Done") -> 0 | D18: =COUNTIFS(Components!$B$2:$B$86,"S16",Components!$P$2:$P$86,"In progress") -> 0 | E18: =COUNTIFS(Components!$B$2:$B$86,"S16",Components!$P$2:$P$86,"Blocked") -> 0 | F18: =IF(B18=0,0,C18/B18) -> 0
A19: S17 | B19: =COUNTIFS(Components!$B$2:$B$86,"S17") -> 1 | C19: =COUNTIFS(Components!$B$2:$B$86,"S17",Components!$P$2:$P$86,"Done") -> 0 | D19: =COUNTIFS(Components!$B$2:$B$86,"S17",Components!$P$2:$P$86,"In progress") -> 0 | E19: =COUNTIFS(Components!$B$2:$B$86,"S17",Components!$P$2:$P$86,"Blocked") -> 0 | F19: =IF(B19=0,0,C19/B19) -> 0
A20: S18 | B20: =COUNTIFS(Components!$B$2:$B$86,"S18") -> 2 | C20: =COUNTIFS(Components!$B$2:$B$86,"S18",Components!$P$2:$P$86,"Done") -> 0 | D20: =COUNTIFS(Components!$B$2:$B$86,"S18",Components!$P$2:$P$86,"In progress") -> 0 | E20: =COUNTIFS(Components!$B$2:$B$86,"S18",Components!$P$2:$P$86,"Blocked") -> 0 | F20: =IF(B20=0,0,C20/B20) -> 0
A21: S19 | B21: =COUNTIFS(Components!$B$2:$B$86,"S19") -> 2 | C21: =COUNTIFS(Components!$B$2:$B$86,"S19",Components!$P$2:$P$86,"Done") -> 0 | D21: =COUNTIFS(Components!$B$2:$B$86,"S19",Components!$P$2:$P$86,"In progress") -> 0 | E21: =COUNTIFS(Components!$B$2:$B$86,"S19",Components!$P$2:$P$86,"Blocked") -> 0 | F21: =IF(B21=0,0,C21/B21) -> 0
A22: Total | B22: =SUM(B2:B21) -> 85 | C22: =SUM(C2:C21) -> 0 | D22: =SUM(D2:D21) -> 0 | E22: =SUM(E2:E21) -> 0 | F22: =IF(B22=0,0,C22/B22) -> 0
A24: P0 components done | B24: =COUNTIFS(Components!$M$2:$M$86,"P0",Components!$P$2:$P$86,"Done")&" / "&COUNTIFS(Components!$M$2:$M$86,"P0") -> 0 / 48
